nw_ssh/__init__.py
nw_ssh/connection.py
nw_ssh/exception.py
nw_ssh/py.typed
nw_ssh-1.0.4.dist-info/LICENSE
nw_ssh-1.0.4.dist-info/WHEEL
nw_ssh-1.0.4.dist-info/METADATA
nw_ssh-1.0.4.dist-info/RECORD
