Metadata-Version: 2.1
Name: nw-ssh
Version: 1.0.4
Summary: Simple ssh client with asyncssh for network devices
Home-page: https://github.com/kthrdei/nw-ssh
License: MIT
Keywords: ssh,network
Author: dei
Requires-Python: >=3.7,<4.0
Classifier: License :: OSI Approved :: MIT License
Classifier: Programming Language :: Python :: 3
Classifier: Programming Language :: Python :: 3.10
Classifier: Programming Language :: Python :: 3.7
Classifier: Programming Language :: Python :: 3.8
Classifier: Programming Language :: Python :: 3.9
Requires-Dist: asyncssh (>=2.4.2,<3.0.0)
Project-URL: Repository, https://github.com/kthrdei/nw-ssh
